dsms/__init__.py
dsms/case_converter.py
dsms/center.py
dsms/command.py
dsms/display.py
dsms/manage.py
dsms/node.py
dsms/router.py
dsms/sock.py
dsms/util.py
dsms/command/__init__.py
dsms/command/admin_command.py
dsms/command/alarm_command.py
dsms/command/bucket_command.py
dsms/command/command.py
dsms/command/project_command.py
dsms/controller/__init__.py
dsms/controller/alarm_controller.py
dsms/controller/center_controller.py
dsms/controller/project_controller.py
dsms/controller/storage_controller.py
dsms/model/__init__.py
dsms/model/alarm_model.py
dsms/model/auth_model.py
dsms/model/project_model.py
dsms/model/storage_model.py
dsms/sdk/__init__.py
dsms/sdk/minio_progress.py
tests/__init__.py
tests/sdk_test.py
tests/slack_test.py
tests/storage_test.py
dsms-0.0.11.dist-info/METADATA
dsms-0.0.11.dist-info/WHEEL
dsms-0.0.11.dist-info/entry_points.txt
dsms-0.0.11.dist-info/top_level.txt
dsms-0.0.11.dist-info/RECORD
