Metadata-Version: 2.1
Name: dsms
Version: 0.0.11
Summary: dsms ai cloud package
Home-page: https://gitlab.com/dudaji/cloud/dsms
Author: dudaji
Author-email: UNKNOWN
License: MIT
Platform: UNKNOWN
Requires-Dist: colorlog
Requires-Dist: fire
Requires-Dist: minio
Requires-Dist: requests
Requires-Dist: terminaltables
Requires-Dist: PyJWT
Requires-Dist: flask
Requires-Dist: flask-cors
Requires-Dist: slackclient
Requires-Dist: flask-socketio
